pakt/__init__.py
pakt/__main__.py
pakt/cli.py
pakt/config.py
pakt/models.py
pakt/plex.py
pakt/scheduler.py
pakt/sync.py
pakt/trakt.py
pakt/tray.py
pakt/assets/icon.png
pakt/assets/icon.svg
pakt/assets/logo.png
pakt/web/__init__.py
pakt/web/app.py
pakt/web/templates/index.html
pakt-0.2.2.dist-info/METADATA
pakt-0.2.2.dist-info/WHEEL
pakt-0.2.2.dist-info/entry_points.txt
pakt-0.2.2.dist-info/RECORD
