Metadata-Version: 2.4
Name: pakt
Version: 0.2.2
Summary: Fast, efficient Plex-Trakt sync using batch API operations
Project-URL: Repository, https://github.com/MikeSiLVO/pakt
Author: MikeSiLVO
License: MIT
Keywords: media,plex,scrobble,sync,trakt
Classifier: Development Status :: 4 - Beta
Classifier: Environment :: Console
Classifier: Intended Audience :: End Users/Desktop
Classifier: License :: OSI Approved :: MIT License
Classifier: Operating System :: OS Independent
Classifier: Programming Language :: Python :: 3.11
Classifier: Programming Language :: Python :: 3.12
Classifier: Topic :: Multimedia :: Video
Requires-Python: >=3.11
Requires-Dist: aiosqlite>=0.19.0
Requires-Dist: apscheduler>=3.10.0
Requires-Dist: click>=8.1.0
Requires-Dist: fastapi>=0.110.0
Requires-Dist: httpx>=0.27.0
Requires-Dist: jinja2>=3.1.0
Requires-Dist: plexapi>=4.15.0
Requires-Dist: pydantic-settings>=2.0.0
Requires-Dist: pydantic>=2.0.0
Requires-Dist: rich>=13.0.0
Requires-Dist: uvicorn>=0.27.0
Provides-Extra: dev
Requires-Dist: pytest-asyncio>=0.23.0; extra == 'dev'
Requires-Dist: pytest>=8.0.0; extra == 'dev'
Requires-Dist: ruff>=0.3.0; extra == 'dev'
Provides-Extra: tray
Requires-Dist: pillow>=10.0.0; extra == 'tray'
Requires-Dist: pystray>=0.19.0; extra == 'tray'
